dnevnik/__init__.py
dnevnik/academic_years.py
dnevnik/base_auth_provider.py
dnevnik/class_unit.py
dnevnik/client.py
dnevnik/group.py
dnevnik/homework_entry.py
dnevnik/mark.py
dnevnik/scheduled_items.py
dnevnik/school.py
dnevnik/student_homework.py
dnevnik/student_profile.py
dnevnik/teacher.py
dnevnik/utils.py
dnevnik/auth_providers/B_login_provider.py
dnevnik/auth_providers/__init__.py
dnevnik/auth_providers/code_based_provider.py
dnevnik/auth_providers/mos_ru.py
dnevnik/auth_providers/selenium_auth.py
dnevnik/auth_providers/token_authorization.py
dnevnik/exceptions/__init__.py
dnevnik/exceptions/auth_exceptions.py
dnevnik/exceptions/request_exceptions.py
dnevnik_mos_ru-2.3.0.dist-info/LICENSE
dnevnik_mos_ru-2.3.0.dist-info/METADATA
dnevnik_mos_ru-2.3.0.dist-info/WHEEL
dnevnik_mos_ru-2.3.0.dist-info/top_level.txt
dnevnik_mos_ru-2.3.0.dist-info/RECORD
