Metadata-Version: 2.1
Name: dnevnik-mos-ru
Version: 2.3.0
Summary: This package is kind of wrapper for dnevnik.mos.ru API service
Home-page: https://github.com/IvanProgramming/dnevnik_mos_ru
Author: Ivan
License: UNKNOWN
Project-URL: Bug Tracker, https://github.com/IvanProgramming/dnevnik_mos_ru/issues
Platform: UNKNOWN
Classifier: Programming Language :: Python :: 3
Classifier: License :: OSI Approved :: MIT License
Classifier: Operating System :: OS Independent
License-File: LICENSE
Requires-Dist: requests
Requires-Dist: selenium
Requires-Dist: bs4
Requires-Dist: lxml
Requires-Dist: pydantic
Requires-Dist: Inject
